apppy/clients/__init__.py
apppy/clients/graphql.py
apppy/clients/codegen/__init__.py
apppy/clients/codegen/pyproject.py
apppy/clients/codegen/runtime.py
apppy/clients/codegen/typescript.py
apppy_clients-0.23.2.dist-info/METADATA
apppy_clients-0.23.2.dist-info/WHEEL
apppy_clients-0.23.2.dist-info/RECORD
