Metadata-Version: 2.4
Name: apppy-clients
Version: 0.23.2
Summary: Infrastructure for generating client packages related to server development
Project-URL: Homepage, https://github.com/spals/apppy
Author: Tim Kral
License: MIT
Classifier: License :: OSI Approved :: MIT License
Classifier: Programming Language :: Python :: 3
Requires-Python: >=3.11
Requires-Dist: graphql-core==3.2.6
Requires-Dist: inflection==0.5.1
